pychaos/__init__.py
pychaos/chaosapi.py
pychaos/chaoslib.py
pychaos-1.0.12.data/scripts/pyLive.py
pychaos-1.0.12.data/scripts/pyPS.py
pychaos-1.0.12.data/scripts/pySendCommand.py
pychaos-1.0.12.data/scripts/pySubscribeNode.py
pychaos-1.0.12.dist-info/METADATA
pychaos-1.0.12.dist-info/WHEEL
pychaos-1.0.12.dist-info/top_level.txt
pychaos-1.0.12.dist-info/RECORD
